using System;
using java.lang;

namespace org.objectweb.asm {
public interface Opcodes {
public static int ASM4 = 4 << 16 | 0 << 8 | 0;
public static int ASM5 = 5 << 16 | 0 << 8 | 0;
public static int V1_1 = 3 << 16 | 45;
public static int V1_2 = 0 << 16 | 46;
public static int V1_3 = 0 << 16 | 47;
public static int V1_4 = 0 << 16 | 48;
public static int V1_5 = 0 << 16 | 49;
public static int V1_6 = 0 << 16 | 50;
public static int V1_7 = 0 << 16 | 51;
public static int V1_8 = 0 << 16 | 52;
public static int ACC_PUBLIC = 0x0001;
public static int ACC_PRIVATE = 0x0002;
public static int ACC_PROTECTED = 0x0004;
public static int ACC_STATIC = 0x0008;
public static int ACC_FINAL = 0x0010;
public static int ACC_SUPER = 0x0020;
public static int ACC_SYNCHRONIZED = 0x0020;
public static int ACC_VOLATILE = 0x0040;
public static int ACC_BRIDGE = 0x0040;
public static int ACC_VARARGS = 0x0080;
public static int ACC_TRANSIENT = 0x0080;
public static int ACC_NATIVE = 0x0100;
public static int ACC_INTERFACE = 0x0200;
public static int ACC_ABSTRACT = 0x0400;
public static int ACC_STRICT = 0x0800;
public static int ACC_SYNTHETIC = 0x1000;
public static int ACC_ANNOTATION = 0x2000;
public static int ACC_ENUM = 0x4000;
public static int ACC_MANDATED = 0x8000;
public static int ACC_DEPRECATED = 0x20000;
public static int T_BOOLEAN = 4;
public static int T_CHAR = 5;
public static int T_FLOAT = 6;
public static int T_DOUBLE = 7;
public static int T_BYTE = 8;
public static int T_SHORT = 9;
public static int T_INT = 10;
public static int T_LONG = 11;
public static int H_GETFIELD = 1;
public static int H_GETSTATIC = 2;
public static int H_PUTFIELD = 3;
public static int H_PUTSTATIC = 4;
public static int H_INVOKEVIRTUAL = 5;
public static int H_INVOKESTATIC = 6;
public static int H_INVOKESPECIAL = 7;
public static int H_NEWINVOKESPECIAL = 8;
public static int H_INVOKEINTERFACE = 9;
public static int F_NEW = -1;
public static int F_FULL = 0;
public static int F_APPEND = 1;
public static int F_CHOP = 2;
public static int F_SAME = 3;
public static int F_SAME1 = 4;
public static int TOP = 0;
public static int INTEGER = 1;
public static int FLOAT = 2;
public static int DOUBLE = 3;
public static int LONG = 4;
public static int NULL = 5;
public static int UNINITIALIZED_THIS = 6;
public static int NOP = 0;
public static int ACONST_NULL = 1;
public static int ICONST_M1 = 2;
public static int ICONST_0 = 3;
public static int ICONST_1 = 4;
public static int ICONST_2 = 5;
public static int ICONST_3 = 6;
public static int ICONST_4 = 7;
public static int ICONST_5 = 8;
public static int LCONST_0 = 9;
public static int LCONST_1 = 10;
public static int FCONST_0 = 11;
public static int FCONST_1 = 12;
public static int FCONST_2 = 13;
public static int DCONST_0 = 14;
public static int DCONST_1 = 15;
public static int BIPUSH = 16;
public static int SIPUSH = 17;
public static int LDC = 18;
public static int ILOAD = 21;
public static int LLOAD = 22;
public static int FLOAD = 23;
public static int DLOAD = 24;
public static int ALOAD = 25;
public static int IALOAD = 46;
public static int LALOAD = 47;
public static int FALOAD = 48;
public static int DALOAD = 49;
public static int AALOAD = 50;
public static int BALOAD = 51;
public static int CALOAD = 52;
public static int SALOAD = 53;
public static int ISTORE = 54;
public static int LSTORE = 55;
public static int FSTORE = 56;
public static int DSTORE = 57;
public static int ASTORE = 58;
public static int IASTORE = 79;
public static int LASTORE = 80;
public static int FASTORE = 81;
public static int DASTORE = 82;
public static int AASTORE = 83;
public static int BASTORE = 84;
public static int CASTORE = 85;
public static int SASTORE = 86;
public static int POP = 87;
public static int POP2 = 88;
public static int DUP = 89;
public static int DUP_X1 = 90;
public static int DUP_X2 = 91;
public static int DUP2 = 92;
public static int DUP2_X1 = 93;
public static int DUP2_X2 = 94;
public static int SWAP = 95;
public static int IADD = 96;
public static int LADD = 97;
public static int FADD = 98;
public static int DADD = 99;
public static int ISUB = 100;
public static int LSUB = 101;
public static int FSUB = 102;
public static int DSUB = 103;
public static int IMUL = 104;
public static int LMUL = 105;
public static int FMUL = 106;
public static int DMUL = 107;
public static int IDIV = 108;
public static int LDIV = 109;
public static int FDIV = 110;
public static int DDIV = 111;
public static int IREM = 112;
public static int LREM = 113;
public static int FREM = 114;
public static int DREM = 115;
public static int INEG = 116;
public static int LNEG = 117;
public static int FNEG = 118;
public static int DNEG = 119;
public static int ISHL = 120;
public static int LSHL = 121;
public static int ISHR = 122;
public static int LSHR = 123;
public static int IUSHR = 124;
public static int LUSHR = 125;
public static int IAND = 126;
public static int LAND = 127;
public static int IOR = 128;
public static int LOR = 129;
public static int IXOR = 130;
public static int LXOR = 131;
public static int IINC = 132;
public static int I2L = 133;
public static int I2F = 134;
public static int I2D = 135;
public static int L2I = 136;
public static int L2F = 137;
public static int L2D = 138;
public static int F2I = 139;
public static int F2L = 140;
public static int F2D = 141;
public static int D2I = 142;
public static int D2L = 143;
public static int D2F = 144;
public static int I2B = 145;
public static int I2C = 146;
public static int I2S = 147;
public static int LCMP = 148;
public static int FCMPL = 149;
public static int FCMPG = 150;
public static int DCMPL = 151;
public static int DCMPG = 152;
public static int IFEQ = 153;
public static int IFNE = 154;
public static int IFLT = 155;
public static int IFGE = 156;
public static int IFGT = 157;
public static int IFLE = 158;
public static int IF_ICMPEQ = 159;
public static int IF_ICMPNE = 160;
public static int IF_ICMPLT = 161;
public static int IF_ICMPGE = 162;
public static int IF_ICMPGT = 163;
public static int IF_ICMPLE = 164;
public static int IF_ACMPEQ = 165;
public static int IF_ACMPNE = 166;
public static int GOTO = 167;
public static int JSR = 168;
public static int RET = 169;
public static int TABLESWITCH = 170;
public static int LOOKUPSWITCH = 171;
public static int IRETURN = 172;
public static int LRETURN = 173;
public static int FRETURN = 174;
public static int DRETURN = 175;
public static int ARETURN = 176;
public static int RETURN = 177;
public static int GETSTATIC = 178;
public static int PUTSTATIC = 179;
public static int GETFIELD = 180;
public static int PUTFIELD = 181;
public static int INVOKEVIRTUAL = 182;
public static int INVOKESPECIAL = 183;
public static int INVOKESTATIC = 184;
public static int INVOKEINTERFACE = 185;
public static int INVOKEDYNAMIC = 186;
public static int NEW = 187;
public static int NEWARRAY = 188;
public static int ANEWARRAY = 189;
public static int ARRAYLENGTH = 190;
public static int ATHROW = 191;
public static int CHECKCAST = 192;
public static int INSTANCEOF = 193;
public static int MONITORENTER = 194;
public static int MONITOREXIT = 195;
public static int MULTIANEWARRAY = 197;
public static int IFNULL = 198;
public static int IFNONNULL = 199;
}
}
